README
libonkyo.py
setup.py
okycmd.egg-info/PKG-INFO
okycmd.egg-info/SOURCES.txt
okycmd.egg-info/dependency_links.txt
okycmd.egg-info/entry_points.txt
okycmd.egg-info/top_level.txt