Metadata-Version: 1.0
Name: okycmd
Version: 0.8
Summary: Network client to onkyo receiver
Home-page: https://github.com/oroulet/okycmd
Author: Olivier R-D
Author-email: UNKNOWN
License: GNU General Public License
Platform: UNKNOWN
